Bubblesk/Demo_video.py
Bubblesk/NNDemo.py
Bubblesk/__init__.py
Bubblesk/nnAPI.py
Bubblesk-1.0.0.dist-info/LICENCE.txt
Bubblesk-1.0.0.dist-info/METADATA
Bubblesk-1.0.0.dist-info/WHEEL
Bubblesk-1.0.0.dist-info/entry_points.txt
Bubblesk-1.0.0.dist-info/top_level.txt
Bubblesk-1.0.0.dist-info/RECORD
