Metadata-Version: 2.1
Name: Bubblesk
Version: 1.0.0
Summary: Bubble_Library
Home-page: UNKNOWN
Author: Sujata
Author-email: UNKNOWN
License: MIT
Platform: UNKNOWN
Classifier: License :: OSI Approved :: MIT License
Classifier: Programming Language :: Python :: 3
Classifier: Programming Language :: Python :: 3.8
